arkindex_cli/__init__.py
arkindex_cli/argtypes.py
arkindex_cli/auth.py
arkindex_cli/cli.py
arkindex_cli/git.py
arkindex_cli/uploads.py
arkindex_cli/utils.py
arkindex_cli/commands/__init__.py
arkindex_cli/commands/benchmark.py
arkindex_cli/commands/classes.py
arkindex_cli/commands/login.py
arkindex_cli/commands/secrets.py
arkindex_cli/commands/utils.py
arkindex_cli/commands/elements/__init__.py
arkindex_cli/commands/elements/link.py
arkindex_cli/commands/elements/ml_splits.py
arkindex_cli/commands/elements/page_copy.py
arkindex_cli/commands/elements/reject_classifications.py
arkindex_cli/commands/elements/unlink.py
arkindex_cli/commands/elements/utils.py
arkindex_cli/commands/export/__init__.py
arkindex_cli/commands/export/alto.py
arkindex_cli/commands/export/csv.py
arkindex_cli/commands/export/docx.py
arkindex_cli/commands/export/entities.py
arkindex_cli/commands/export/pagexml.py
arkindex_cli/commands/export/pdf.py
arkindex_cli/commands/export/utils.py
arkindex_cli/commands/models/__init__.py
arkindex_cli/commands/models/publish.py
arkindex_cli/commands/models/utils.py
arkindex_cli/commands/selection/__init__.py
arkindex_cli/commands/selection/populate.py
arkindex_cli/commands/upload/__init__.py
arkindex_cli/commands/upload/cache.py
arkindex_cli/commands/upload/data_file.py
arkindex_cli/commands/upload/db.py
arkindex_cli/commands/upload/exceptions.py
arkindex_cli/commands/upload/iiif.py
arkindex_cli/commands/upload/minio_client.py
arkindex_cli/commands/upload/model_version.py
arkindex_cli/commands/upload/page_xml_import.py
arkindex_cli/commands/upload/alto/__init__.py
arkindex_cli/commands/upload/alto/parser.py
arkindex_cli/commands/upload/mets/__init__.py
arkindex_cli/commands/upload/mets/parser.py
arkindex_cli/commands/worker/__init__.py
arkindex_cli/commands/worker/import_worker.py
arkindex_cli/commands/worker/publish.py
tests/conftest.py
tests/test_alto_export_mets.py
tests/test_alto_upload.py
tests/test_argtypes.py
tests/test_auth.py
arkindex_cli-0.4.10.dist-info/METADATA
arkindex_cli-0.4.10.dist-info/WHEEL
arkindex_cli-0.4.10.dist-info/entry_points.txt
arkindex_cli-0.4.10.dist-info/top_level.txt
arkindex_cli-0.4.10.dist-info/RECORD
