Metadata-Version: 2.4
Name: arkindex-cli
Version: 0.4.10
Summary: Arkindex CLI client easy and sexy to use
Author-email: Teklia <contact@teklia.com>
Maintainer-email: Teklia <contact@teklia.com>
Project-URL: Homepage, https://cli.arkindex.org/
Project-URL: Documentation, https://cli.arkindex.org/
Project-URL: Repository, https://gitlab.teklia.com/arkindex/cli/
Project-URL: Bug Tracker, https://gitlab.teklia.com/arkindex/cli/issues/
Project-URL: Authors, https://teklia.com
Keywords: python
Classifier: Development Status :: 5 - Production/Stable
Classifier: Programming Language :: Python :: 3 :: Only
Classifier: Programming Language :: Python :: 3.10
Classifier: Programming Language :: Python :: 3.11
Requires-Python: >=3.10
Requires-Dist: arkindex-export==0.2.0
Requires-Dist: minio==7.2.7
Requires-Dist: python-dateutil==2.9.0.post0
Requires-Dist: python-docx==1.1.2
Requires-Dist: python-gnupg==0.5.4
Requires-Dist: python-magic==0.4.27
Requires-Dist: rich==13.7.1
Requires-Dist: teklia-toolbox==0.1.11
Requires-Dist: teklia-worker-configuration==0.1.0
Requires-Dist: zstandard==0.23.0
Provides-Extra: export
Requires-Dist: reportlab==4.2.5; extra == "export"
Provides-Extra: tests
Requires-Dist: pytest==7.4.2; extra == "tests"
Requires-Dist: pytest-mock==3.14.0; extra == "tests"
Requires-Dist: pytest-responses==0.5.1; extra == "tests"
